rara_meta_extractor/__init__.py
rara_meta_extractor/config.py
rara_meta_extractor/epub_meta_extractor.py
rara_meta_extractor/exceptions.py
rara_meta_extractor/llama_api_wrapper.py
rara_meta_extractor/llama_extractor.py
rara_meta_extractor/llm_agents.py
rara_meta_extractor/meta_extractor.py
rara_meta_extractor/mets_alto_meta_extractor.py
rara_meta_extractor/regex_extractors.py
rara_meta_extractor/constants/data_classes.py
rara_meta_extractor/constants/patterns.py
rara_meta_extractor/constants/schemas.py
rara_meta_extractor/data/field_translations/author_roles.json
rara_meta_extractor/data/field_translations/meta_field_map.json
rara_meta_extractor/data/fields/author_fields.txt
rara_meta_extractor/data/fields/epub_meta_keys.txt
rara_meta_extractor/data/fields/kata_author_fields.txt
rara_meta_extractor/data/fields/kata_meta_fields.txt
rara_meta_extractor/data/instructions/meta_extractor_instructions.txt
rara_meta_extractor/data/instructions/text_classifier_instructions.txt
rara_meta_extractor/data/schemas/meta_schema.json
rara_meta_extractor/text_part_classifiers/base_text_part_classifier.py
rara_meta_extractor/text_part_classifiers/epub_text_part_classifier.py
rara_meta_extractor/text_part_classifiers/mets_alto_text_part_classifier.py
rara_meta_extractor/text_part_classifiers/regex_text_part_classifier.py
rara_meta_extractor/tools/epub_llama_merger.py
rara_meta_extractor/tools/llama_schema_generator.py
rara_meta_extractor/tools/llama_validator.py
rara_meta_extractor/tools/meta_formatter.py
rara_meta_extractor/tools/utils.py
rara_meta_extractor-2.2.0.dist-info/licenses/LICENSE
tests/test_epub_meta_extractor.py
tests/test_epub_text_part_classifier.py
tests/test_isbn_regex_extractor.py
tests/test_mets_alto_meta_extractor.py
tests/test_mets_alto_text_part_classifier.py
tests/test_regex_text_part_classifier.py
tests/test_various.py
rara_meta_extractor-2.2.0.dist-info/METADATA
rara_meta_extractor-2.2.0.dist-info/WHEEL
rara_meta_extractor-2.2.0.dist-info/top_level.txt
rara_meta_extractor-2.2.0.dist-info/RECORD
