Metadata-Version: 2.4
Name: rara-meta-extractor
Version: 2.2.0
Summary: Extracts relevant meta information for cataloging.
License:                     GNU AFFERO GENERAL PUBLIC LICENSE
Classifier: Programming Language :: Python :: 3
Classifier: Programming Language :: Python :: 3.10
Classifier: Programming Language :: Python :: 3.11
Classifier: Programming Language :: Python :: 3.12
Classifier: Intended Audience :: Science/Research
Requires-Python: >=3.10
License-File: LICENSE
Requires-Dist: requests
Requires-Dist: regex
Requires-Dist: jsonlines
Requires-Dist: beautifulsoup4
Requires-Dist: lxml
Requires-Dist: langdetect
Requires-Dist: rara-tools==0.9.*
Provides-Extra: testing
Requires-Dist: pytest>=8.0; extra == "testing"
Requires-Dist: pytest-order; extra == "testing"
Dynamic: license-file
